.DS_Store
nuketemplate/__init__.py
nuketemplate/build.py
nuketemplate/convert.py
nuketemplate/exceptions.py
nuketemplate/graph.py
nuketemplate/template.py
nuketemplate-0.2.0.dist-info/DESCRIPTION.rst
nuketemplate-0.2.0.dist-info/LICENSE.txt
nuketemplate-0.2.0.dist-info/METADATA
nuketemplate-0.2.0.dist-info/RECORD
nuketemplate-0.2.0.dist-info/WHEEL
nuketemplate-0.2.0.dist-info/metadata.json
nuketemplate-0.2.0.dist-info/top_level.txt
