Metadata-Version: 2.0
Name: nuketemplate
Version: 0.2.0
Summary: A toolkit to build Nuke scripts with flexible templates, based on Jinja 2
Home-page: https://github.com/florianeinfalt/nuketemplate
Author: Florian Einfalt
Author-email: info@florianeinfalt.de
License: Apache 2.0
Platform: UNKNOWN
Classifier: Development Status :: 3 - Alpha
Classifier: Intended Audience :: Developers
Classifier: Natural Language :: English
Classifier: Topic :: Software Development :: Build Tools
Classifier: License :: OSI Approved :: Apache Software License
Classifier: Programming Language :: Python
Classifier: Programming Language :: Python :: 2.6
Classifier: Programming Language :: Python :: 2.7
Classifier: Programming Language :: Python :: Implementation :: CPython
Requires-Dist: attrs
Requires-Dist: jinja2
Requires-Dist: networkx
Requires-Dist: nukecontexts
Requires-Dist: nukeuuid
Requires-Dist: pydotplus
